[
  {
    "tables": [
      {
        "table_schema": "CREATE TABLE blockchain_data (\n\tblock_id INT,\n\tblock_hash VARCHAR(255),\n\ttimestamp TIMESTAMP,\n\ttransaction_count INT\n);"
      }
    ]
  },
  {
    "tables": [
      {
        "table_schema": "CREATE TABLE blockchain_data (\n  block_number INT,\n  block_timestamp TIMESTAMP,\n  transaction_id UUID,\n  sender_address VARCHAR(255),\n  receiver_address VARCHAR(255),\n  transaction_amount DECIMAL,\n  PRIMARY KEY (block_number, transaction_id)\n);"
      },
      {
        "table_schema": "CREATE TABLE transaction_history (\n  transaction_id UUID,\n  block_number INT,\n  sender_address VARCHAR(255),\n  receiver_address VARCHAR(255),\n  transaction_amount DECIMAL,\n  transaction_date DATE,\n  PRIMARY KEY (transaction_id)\n);"
      }
    ]
  },
  {
    "tables": [
      {
        "table_schema": "CREATE TABLE blockchain_data (\n   block_id UUID PRIMARY KEY,\n   timestamp TIMESTAMP,\n   transaction_count INT,\n   miner_address VARCHAR(255)\n);"
      },
      {
        "table_schema": "CREATE TABLE transactions (\n   transaction_id UUID PRIMARY KEY,\n   block_id UUID,\n   sender_address VARCHAR(255),\n   receiver_address VARCHAR(255),\n   amount DECIMAL(18, 2)\n);"
      },
      {
        "table_schema": "CREATE TABLE block_miners (\n   miner_id UUID PRIMARY KEY,\n   miner_address VARCHAR(255),\n   block_count INT\n);"
      }
    ]
  },
  {
    "tables": [
      {
        "table_schema": "CREATE TABLE blockchain_data (\n    block_id INT PRIMARY KEY,\n    block_hash VARCHAR(255),\n    timestamp TIMESTAMP,\n    transactions INT\n);"
      },
      {
        "table_schema": "CREATE TABLE transactions (\n    transaction_id INT PRIMARY KEY,\n    sender_address VARCHAR(255),\n    receiver_address VARCHAR(255),\n    amount DECIMAL,\n    timestamp TIMESTAMP\n);"
      },
      {
        "table_schema": "CREATE TABLE addresses (\n    address_id INT PRIMARY KEY,\n    address VARCHAR(255),\n    balance DECIMAL\n);"
      },
      {
        "table_schema": "CREATE TABLE blocks (\n    block_id INT PRIMARY KEY,\n    num_transactions INT,\n    miner_address VARCHAR(255),\n    timestamp TIMESTAMP\n);"
      }
    ]
  },
  {
    "tables": [
      {
        "table_schema": "CREATE TABLE BlockchainData (\n    block_number BIGINT PRIMARY KEY,\n    transaction_hash UUID,\n    timestamp TIMESTAMPTZ,\n    transaction_count INT\n);\n"
      },
      {
        "table_schema": "CREATE TABLE Transactions (\n    transaction_id SERIAL PRIMARY KEY,\n    block_number BIGINT,\n    sender_address VARCHAR(255),\n    receiver_address VARCHAR(255),\n    amount NUMERIC(15, 2),\n    fee NUMERIC(10, 2)\n);\n"
      },
      {
        "table_schema": "CREATE TABLE Blocks (\n    block_number BIGINT PRIMARY KEY,\n    miner_address VARCHAR(255),\n    block_hash UUID,\n    timestamp TIMESTAMPTZ,\n    transaction_count INT\n);\n"
      },
      {
        "table_schema": "CREATE TABLE Addresses (\n    address_id SERIAL PRIMARY KEY,\n    address VARCHAR(255),\n    created_date DATE\n);\n"
      },
      {
        "table_schema": "CREATE TABLE TransactionsHistory (\n    transaction_id SERIAL PRIMARY KEY,\n    timestamp TIMESTAMPTZ,\n    block_number BIGINT,\n    sender_address VARCHAR(255),\n    receiver_address VARCHAR(255),\n    amount NUMERIC(15, 2)\n);\n"
      }
    ]
  }
]