[
  {
    "tables": [
      {
        "table_schema": "CREATE TABLE tenants (\n  tenant_id INT PRIMARY KEY,\n  tenant_name VARCHAR(255),\n  contact_number VARCHAR(15),\n  email VARCHAR(255),\n  lease_start_date DATE,\n  lease_end_date DATE\n)"
      }
    ]
  },
  {
    "tables": [
      {
        "table_schema": "CREATE TABLE TenantInformation (\n    tenant_id UUID PRIMARY KEY,\n    full_name VARCHAR,\n    contact_number VARCHAR,\n    email VARCHAR\n);"
      },
      {
        "table_schema": "CREATE TABLE LeaseAgreements (\n    lease_id UUID PRIMARY KEY,\n    tenant_id UUID REFERENCES TenantInformation(tenant_id),\n    lease_start_date DATE,\n    lease_end_date DATE,\n    rent_amount DECIMAL\n);"
      }
    ]
  },
  {
    "tables": [
      {
        "table_schema": "CREATE TABLE TenantInformation (\n    tenant_id UUID PRIMARY KEY,\n    tenant_name VARCHAR(255),\n    email VARCHAR(255),\n    phone_number VARCHAR(15)\n);\n"
      },
      {
        "table_schema": "CREATE TABLE ContactDetails (\n    contact_id UUID PRIMARY KEY,\n    tenant_id UUID,\n    address VARCHAR(255),\n    city VARCHAR(100),\n    state VARCHAR(50),\n    postal_code VARCHAR(10)\n);\n"
      },
      {
        "table_schema": "CREATE TABLE LeaseAgreements (\n    lease_id UUID PRIMARY KEY,\n    tenant_id UUID,\n    start_date DATE,\n    end_date DATE,\n    rent_amount DECIMAL(10, 2)\n);\n"
      }
    ]
  },
  {
    "tables": [
      {
        "table_schema": "CREATE TABLE tenants (\n    id INT PRIMARY KEY,\n    name VARCHAR(255),\n    email VARCHAR(255),\n    phone_number VARCHAR(20),\n    lease_agreement_id INT\n);\n"
      },
      {
        "table_schema": "CREATE TABLE contact_details (\n    id INT PRIMARY KEY,\n    tenant_id INT,\n    address VARCHAR(255),\n    city VARCHAR(100),\n    state VARCHAR(50),\n    zipcode VARCHAR(10)\n);\n"
      },
      {
        "table_schema": "CREATE TABLE lease_agreements (\n    id INT PRIMARY KEY,\n    tenant_id INT,\n    start_date DATE,\n    end_date DATE,\n    monthly_rent DECIMAL(10, 2)\n);\n"
      },
      {
        "table_schema": "CREATE TABLE payments (\n    id INT PRIMARY KEY,\n    lease_agreement_id INT,\n    payment_date DATE,\n    amount DECIMAL(10, 2)\n);\n"
      }
    ]
  },
  {
    "tables": [
      {
        "table_schema": "CREATE TABLE tenants (\n    tenant_id INT PRIMARY KEY,\n    first_name VARCHAR(50),\n    last_name VARCHAR(50),\n    email VARCHAR(100),\n    phone_number VARCHAR(20)\n);"
      },
      {
        "table_schema": "CREATE TABLE addresses (\n    address_id INT PRIMARY KEY,\n    tenant_id INT REFERENCES tenants (tenant_id),\n    street_address VARCHAR(100),\n    city VARCHAR(50),\n    state VARCHAR(50),\n    postal_code VARCHAR(20)\n);"
      },
      {
        "table_schema": "CREATE TABLE lease_agreements (\n    agreement_id INT PRIMARY KEY,\n    tenant_id INT REFERENCES tenants (tenant_id),\n    start_date DATE,\n    end_date DATE,\n    rent_amount DECIMAL(10, 2)\n);"
      },
      {
        "table_schema": "CREATE TABLE payments (\n    payment_id INT PRIMARY KEY,\n    agreement_id INT REFERENCES lease_agreements (agreement_id),\n    payment_date DATE,\n    amount DECIMAL(10, 2)\n);"
      },
      {
        "table_schema": "CREATE TABLE notifications (\n    notification_id INT PRIMARY KEY,\n    tenant_id INT REFERENCES tenants (tenant_id),\n    message TEXT,\n    date_sent TIMESTAMP\n);"
      }
    ]
  }
]