[
  {
    "statements": [
      "DELETE FROM retirement_transactions WHERE transaction_id = 1001;",
      "DELETE FROM retirement_transactions WHERE transaction_type = 'withdrawal' AND account_id = 2001;",
      "DELETE FROM retirement_transactions WHERE transaction_id = 1001;",
      "DELETE FROM retirement_transactions WHERE account_id = 2002 AND transaction_type = 'Withdrawal';"
    ]
  },
  {
    "statements": [
      "DELETE FROM contributions WHERE id = 1;",
      "DELETE FROM withdrawals WHERE account_id = 100 AND amount > 500;",
      "DELETE FROM contributions WHERE id = 1",
      "DELETE FROM withdrawals WHERE account_id = 100 AND amount > 500"
    ]
  },
  {
    "statements": [
      "DELETE FROM retirement_contributions WHERE user_id = 123;",
      "DELETE FROM account_balances WHERE user_id = 456;",
      "DELETE FROM retirement_contributions WHERE id = 5;",
      "DELETE FROM withdrawal_transactions WHERE user_id = 12;"
    ]
  },
  {
    "statements": [
      "DELETE FROM accounts WHERE id = 1;",
      "DELETE FROM contributions WHERE contribution_date < '2022-01-01';",
      "DELETE FROM contributions WHERE id = 1;",
      "DELETE FROM accounts WHERE owner_name = 'John Doe';"
    ]
  },
  {
    "statements": [
      "DELETE FROM contributions WHERE account_id = 101;",
      "DELETE FROM withdrawals WHERE withdrawal_date = '2022-04-15';",
      "DELETE FROM contributions WHERE account_id = 101 AND contribution_date < '2022-01-01';",
      "DELETE FROM withdrawals WHERE withdrawal_amount > 1000 AND reason = 'Overdraft';"
    ]
  }
]