[
  {
    "statements": [
      "TRUNCATE TABLE secure_data;",
      "TRUNCATE TABLE secure_data;",
      "TRUNCATE secure_data;",
      "TRUNCATE secure_data CASCADE;"
    ]
  },
  {
    "statements": [
      "TRUNCATE TABLE secure_data;",
      "TRUNCATE TABLE transmission_logs;",
      "TRUNCATE TABLE transmission_logs;",
      "TRUNCATE TABLE secure_data;"
    ]
  },
  {
    "statements": [
      "TRUNCATE TABLE data_encryption",
      "TRUNCATE TABLE transmission_logs",
      "TRUNCATE TABLE data_encryption",
      "TRUNCATE TABLE transmission_logs"
    ]
  },
  {
    "statements": [
      "TRUNCATE TABLE users;",
      "TRUNCATE TABLE permissions;",
      "TRUNCATE TABLE secure_data;",
      "TRUNCATE TABLE permissions;"
    ]
  },
  {
    "statements": [
      "TRUNCATE TABLE addresses;",
      "TRUNCATE TABLE products",
      "TRUNCATE TABLE transactions, orders, addresses, products, users;",
      "TRUNCATE TABLE orders, transactions, users, products, addresses;"
    ]
  }
]