[
  {
    "statements": [
      "UPDATE customers SET first_name='John', last_name='Doe', city='New York' WHERE customer_id=1;",
      "UPDATE customers SET email_address='johndoe@example.com', phone_number='123-456-7890', country='USA' WHERE customer_id=2;",
      "UPDATE customers SET first_name = 'John', last_name = 'Doe', email_address = 'john.doe@example.com' WHERE customer_id = 1;",
      "UPDATE customers SET city = 'Los Angeles', state = 'California', country = 'USA' WHERE customer_id = 2;"
    ]
  },
  {
    "statements": [
      "UPDATE customers SET first_name='John', last_name='Doe', email='john.doe@email.com' WHERE customer_id=1;",
      "UPDATE campaigns SET campaign_name='Summer Sale', customer_id=2, end_date='2022-08-31', start_date='2022-06-01' WHERE campaign_id=3;",
      "UPDATE customers SET first_name = 'John', last_name = 'Doe' WHERE customer_id = 1;",
      "UPDATE campaigns SET start_date = '2022-01-01', end_date = '2022-12-31' WHERE campaign_id = 5;"
    ]
  },
  {
    "statements": [
      "UPDATE customers SET email_address = 'newemail@example.com', phone_number = '+1234567890' WHERE customer_id = 1;",
      "UPDATE campaigns SET start_date = '2022-06-30', target_audience = 'New Target Audience' WHERE campaign_id = 3;",
      "UPDATE customers SET email_address = 'newemail@example.com', phone_number = '+1234567890' WHERE customer_id = 1;",
      "UPDATE campaigns SET start_date = '2022-10-15', target_audience = 'New Target Audience' WHERE campaign_id = 5;"
    ]
  },
  {
    "statements": [
      "UPDATE customers SET first_name = 'John', last_name = 'Doe' WHERE customer_id = '123e4567-e89b-12d3-a456-426614174000';",
      "UPDATE campaign_history SET opened = TRUE, clicked = FALSE WHERE campaign_id = '98765432-1234-5678-90ab-cdef01234567' AND segment_id = '456789ab-5678-9abc-def0-123456789abc';",
      "UPDATE customers SET first_name = 'John', email = 'john@example.com' WHERE customer_id = '4567890-1234-5678-9012-345678901234';",
      "UPDATE campaign_history SET opened = TRUE, clicked = TRUE, sent_date = '2022-01-15 08:30:00' WHERE customer_id = '9876543-2109-8765-4321-098765432109' AND campaign_id = '1234567-8901-2345-6789-012345678901' AND segment_id = '5678901-2345-6789-0123-456789012345';"
    ]
  },
  {
    "statements": [
      "UPDATE customers SET first_name='John', last_name='Doe', address='123 Main St' WHERE customer_id=1;",
      "UPDATE campaigns SET budget=1500.00, end_date='2023-06-30', campaign_name='Summer Sale' WHERE campaign_id=3;",
      "UPDATE customers SET address='123 Main St' WHERE customer_id=1",
      "UPDATE messages SET message_text='New message text', send_date='2022-08-15 10:00:00' WHERE message_id=5"
    ]
  }
]