[
  {
    "statements": [
      "TRUNCATE TABLE eco_friendly_vehicles_maintenance_schedule;",
      "TRUNCATE TABLE eco_friendly_vehicles_maintenance_schedule;",
      "TRUNCATE TABLE eco_friendly_vehicles_maintenance_schedule",
      "TRUNCATE TABLE eco_friendly_vehicles_maintenance_schedule;"
    ]
  },
  {
    "statements": [
      "TRUNCATE TABLE maintenance_schedule;",
      "TRUNCATE TABLE maintenance_record;",
      "TRUNCATE TABLE maintenance_record",
      "TRUNCATE TABLE maintenance_schedule"
    ]
  },
  {
    "statements": [
      "TRUNCATE TABLE MaintenanceRecords;",
      "TRUNCATE TABLE EcoFriendlyVehicles;",
      "TRUNCATE TABLE EcoFriendlyVehicles",
      "TRUNCATE TABLE MaintenanceRecords"
    ]
  },
  {
    "statements": [
      "TRUNCATE TABLE maintenance_schedule;",
      "TRUNCATE TABLE fleet_management;",
      "TRUNCATE TABLE maintenance_schedule;",
      "TRUNCATE TABLE fleet_management;"
    ]
  },
  {
    "statements": [
      "TRUNCATE TABLE maintenance_logs;",
      "TRUNCATE TABLE maintenance_records;",
      "TRUNCATE TABLE maintenance_logs;",
      "TRUNCATE TABLE maintenance_personnel;"
    ]
  }
]