[
  {
    "statements": [
      "TRUNCATE TABLE patient_medical_records;",
      "TRUNCATE patient_medical_records;",
      "TRUNCATE TABLE patient_medical_records;",
      "TRUNCATE TABLE patient_medical_records CASCADE;"
    ]
  },
  {
    "statements": [
      "TRUNCATE TABLE patients;",
      "TRUNCATE TABLE medical_records;",
      "TRUNCATE TABLE medical_records;",
      "TRUNCATE TABLE patients;"
    ]
  },
  {
    "statements": [
      "TRUNCATE TABLE lab_results;",
      "TRUNCATE TABLE treatment_history;",
      "TRUNCATE TABLE lab_results;",
      "TRUNCATE TABLE treatment_history;"
    ]
  },
  {
    "statements": [
      "TRUNCATE TABLE patients;",
      "TRUNCATE TABLE medical_records;",
      "TRUNCATE TABLE treatments;",
      "TRUNCATE TABLE medical_records;"
    ]
  },
  {
    "statements": [
      "TRUNCATE TABLE consultations;",
      "TRUNCATE TABLE medical_staff;",
      "TRUNCATE TABLE consultations, lab_results, medical_staff",
      "TRUNCATE TABLE treatments;"
    ]
  }
]