[
  {
    "statements": [
      "TRUNCATE TABLE stock_market_data;",
      "TRUNCATE TABLE stock_market_data;",
      "TRUNCATE TABLE stock_market_data;",
      "TRUNCATE TABLE stock_market_data CASCADE;"
    ]
  },
  {
    "statements": [
      "TRUNCATE TABLE HistoricalStockData;",
      "TRUNCATE TABLE StockAnalysis;",
      "TRUNCATE TABLE StockAnalysis;",
      "TRUNCATE TABLE HistoricalStockData;"
    ]
  },
  {
    "statements": [
      "TRUNCATE TABLE historical_stock_data;",
      "TRUNCATE TABLE stock_forecasts;",
      "TRUNCATE TABLE historical_stock_data;",
      "TRUNCATE TABLE stock_forecasts;"
    ]
  },
  {
    "statements": [
      "TRUNCATE TABLE stocks;",
      "TRUNCATE TABLE stock_trades;",
      "TRUNCATE TABLE stocks;",
      "TRUNCATE TABLE stock_prices;"
    ]
  },
  {
    "statements": [
      "TRUNCATE TABLE stock_transactions;",
      "TRUNCATE TABLE stock_prices;",
      "TRUNCATE TABLE stock_prices;",
      "TRUNCATE TABLE stock_transactions;"
    ]
  }
]