[
  {
    "statements": [
      "TRUNCATE TABLE voting_data;",
      "TRUNCATE TABLE voting_data;",
      "TRUNCATE TABLE voting_data;",
      "TRUNCATE TABLE voting_data CASCADE;"
    ]
  },
  {
    "statements": [
      "TRUNCATE TABLE voting_records;",
      "TRUNCATE TABLE election_results;",
      "TRUNCATE TABLE voting_records;",
      "TRUNCATE TABLE election_results;"
    ]
  },
  {
    "statements": [
      "TRUNCATE TABLE voting_data;",
      "TRUNCATE TABLE candidate_status;",
      "TRUNCATE TABLE election_results;",
      "TRUNCATE TABLE candidate_status;"
    ]
  },
  {
    "statements": [
      "TRUNCATE TABLE VotingRecords;",
      "TRUNCATE TABLE Candidates;",
      "TRUNCATE TABLE VotingRecords;",
      "TRUNCATE TABLE Voters;"
    ]
  },
  {
    "statements": [
      "TRUNCATE TABLE votes;",
      "TRUNCATE TABLE election_results;",
      "TRUNCATE TABLE voters;",
      "TRUNCATE TABLE votes;"
    ]
  }
]