[
  {
    "tables": [
      {
        "table_schema": "CREATE TABLE project_milestones (\n    milestone_id INT PRIMARY KEY,\n    milestone_name VARCHAR(255) NOT NULL,\n    project_id INT NOT NULL,\n    timeline_id INT NOT NULL,\n    milestone_date DATE\n);\n"
      }
    ]
  },
  {
    "tables": [
      {
        "table_schema": "CREATE TABLE project_milestones (\n    milestone_id INT PRIMARY KEY,\n    milestone_name VARCHAR(255),\n    project_id INT,\n    milestone_description TEXT\n);"
      },
      {
        "table_schema": "CREATE TABLE project_timelines (\n    timeline_id INT PRIMARY KEY,\n    project_id INT,\n    start_date DATE,\n    end_date DATE,\n    milestone_id INT\n);"
      }
    ]
  },
  {
    "tables": [
      {
        "table_schema": "CREATE TABLE project_milestones (\n\tid INT PRIMARY KEY,\n\tname VARCHAR,\n\tdescription TEXT,\n\tstatus VARCHAR\n);"
      },
      {
        "table_schema": "CREATE TABLE project_timelines (\n\tid INT PRIMARY KEY,\n\ttimeline_date TIMESTAMP,\n\tcurrent_progress INT,\n\tproject_id INT,\n\tFOREIGN KEY (project_id) REFERENCES project_milestones(id)\n);"
      },
      {
        "table_schema": "CREATE TABLE project_teams (\n\tid INT PRIMARY KEY,\n\tteam_name VARCHAR,\n\tteam_lead VARCHAR,\n\tproject_id INT,\n\tFOREIGN KEY (project_id) REFERENCES project_milestones(id)\n);"
      }
    ]
  },
  {
    "tables": [
      {
        "table_schema": "CREATE TABLE project_milestones (\n    milestone_id INT PRIMARY KEY,\n    milestone_name TEXT,\n    project_id INT,\n    milestone_date DATE\n);"
      },
      {
        "table_schema": "CREATE TABLE project_timelines (\n    timeline_id INT PRIMARY KEY,\n    project_id INT,\n    start_date DATE,\n    end_date DATE\n);"
      },
      {
        "table_schema": "CREATE TABLE project_progress (\n    progress_id INT PRIMARY KEY,\n    project_id INT,\n    milestone_id INT,\n    progress_status TEXT,\n    progress_date DATE\n);"
      },
      {
        "table_schema": "CREATE TABLE project_team (\n    team_id INT PRIMARY KEY,\n    project_id INT,\n    team_name TEXT,\n    team_lead TEXT,\n    team_members TEXT\n);"
      }
    ]
  },
  {
    "tables": [
      {
        "table_schema": "CREATE TABLE project_milestones (\n    milestone_id UUID PRIMARY KEY,\n    project_id UUID,\n    milestone_name TEXT,\n    due_date DATE\n);"
      },
      {
        "table_schema": "CREATE TABLE project_timelines (\n    timeline_id UUID PRIMARY KEY,\n    project_id UUID,\n    start_date DATE,\n    end_date DATE\n);"
      },
      {
        "table_schema": "CREATE TABLE milestone_progress (\n    milestone_id UUID,\n    project_id UUID,\n    progress_percentage INT\n);"
      },
      {
        "table_schema": "CREATE TABLE project_status (\n    project_id UUID PRIMARY KEY,\n    status TEXT,\n    current_progress INT\n);"
      },
      {
        "table_schema": "CREATE TABLE project_team (\n    project_id UUID,\n    user_id UUID,\n    role TEXT\n);"
      }
    ]
  }
]