[
  {
    "statements": [
      "TRUNCATE TABLE MusicTheoryExercises;",
      "TRUNCATE MusicTheoryExercises;",
      "TRUNCATE TABLE MusicTheoryExercises;",
      "TRUNCATE TABLE MusicTheoryExercises CASCADE;"
    ]
  },
  {
    "statements": [
      "TRUNCATE exercises;",
      "TRUNCATE quizzes;",
      "TRUNCATE TABLE exercises;",
      "TRUNCATE TABLE quizzes;"
    ]
  },
  {
    "statements": [
      "TRUNCATE TABLE music_exercises;",
      "TRUNCATE TABLE music_quizzes;",
      "TRUNCATE TABLE student_progress;",
      "TRUNCATE TABLE music_quizzes;"
    ]
  },
  {
    "statements": [
      "TRUNCATE exercises;",
      "TRUNCATE student_scores;",
      "TRUNCATE TABLE exercises, quizzes, student_scores, student_progress CASCADE;",
      "TRUNCATE TABLE student_scores, student_progress, quizzes, exercises CASCADE;"
    ]
  },
  {
    "statements": [
      "TRUNCATE TABLE student_progress;",
      "TRUNCATE TABLE questions;",
      "TRUNCATE TABLE student_progress;",
      "TRUNCATE TABLE answers;"
    ]
  }
]