[
  {
    "statements": [
      "UPDATE inventory_management SET product_name = 'Chair', stock_quantity = 100 WHERE hub_id = 1;",
      "UPDATE inventory_management SET product_name = 'Table' WHERE hub_id = 2;",
      "UPDATE inventory_management SET stock_quantity = 150, product_name = 'Updated Product 1' WHERE hub_id = 1 AND product_id = 101",
      "UPDATE inventory_management SET product_name = 'New Product 2', stock_quantity = 200 WHERE hub_id = 2 AND product_id = 202"
    ]
  },
  {
    "statements": [
      "UPDATE inventory_levels SET current_stock = 50, min_stock_threshold = 10 WHERE id = 1;",
      "UPDATE delivery_hubs SET location = 'New Location' WHERE id = 3;",
      "UPDATE inventory_levels SET current_stock = 50, min_stock_threshold = 10 WHERE id = 1;",
      "UPDATE delivery_hubs SET capacity = 100, location = 'New Location' WHERE id = 3;"
    ]
  },
  {
    "statements": [
      "UPDATE inventory_level SET quantity = 20 WHERE product_name = 'Chair';",
      "UPDATE stock_availability SET quantity_available = 1000 WHERE product_id = 5 AND hub_id = 3;",
      "UPDATE inventory_level SET quantity = 100, product_name = 'Laptop' WHERE id = 1;",
      "UPDATE stock_availability SET quantity_available = 50 WHERE product_id = 2 AND hub_id = 3;"
    ]
  },
  {
    "statements": [
      "UPDATE delivery_hub SET hub_location = 'New Location' WHERE hub_id = 1;",
      "UPDATE product SET price = 49.99 WHERE product_id = 3;",
      "UPDATE delivery_hub SET hub_location = 'New York' WHERE hub_id = 1;",
      "UPDATE product SET price = 29.99, category = 'Electronics' WHERE product_id = 3;"
    ]
  },
  {
    "statements": [
      "UPDATE delivery_hubs SET location = 'New Location' WHERE hub_id = 1;",
      "UPDATE inventory_items SET price = 15.99 WHERE item_id = 3;",
      "UPDATE delivery_hubs SET hub_name = 'New Hub Name' WHERE hub_id = 1;",
      "UPDATE inventory_items SET price = 15.99 WHERE item_id = 5;"
    ]
  }
]