[
  {
    "statements": [
      "TRUNCATE TABLE rma_tracking;",
      "TRUNCATE TABLE rma_tracking RESTART IDENTITY;",
      "TRUNCATE TABLE rma_tracking;",
      "TRUNCATE rma_tracking;"
    ]
  },
  {
    "statements": [
      "TRUNCATE TABLE rma_history;",
      "TRUNCATE TABLE rma_requests;",
      "TRUNCATE TABLE rma_history;",
      "TRUNCATE TABLE rma_requests;"
    ]
  },
  {
    "statements": [
      "TRUNCATE TABLE RMA_Request;",
      "TRUNCATE TABLE RMA_Return;",
      "TRUNCATE TABLE RMA_Request;",
      "TRUNCATE TABLE RMA_Return;"
    ]
  },
  {
    "statements": [
      "TRUNCATE TABLE RMAResolution;",
      "TRUNCATE TABLE RMARequest;",
      "TRUNCATE TABLE RMARequest, RMAResolution, RMALog, RMACustomerFeedback;",
      "TRUNCATE TABLE RMAResolution, RMARequest, RMACustomerFeedback, RMALog;"
    ]
  },
  {
    "statements": [
      "TRUNCATE TABLE Returns;",
      "TRUNCATE TABLE Replacements;",
      "TRUNCATE TABLE Replacements;",
      "TRUNCATE TABLE Returns;"
    ]
  }
]