[
  {
    "statements": [
      "TRUNCATE TABLE warehouse_layout;",
      "TRUNCATE TABLE warehouse_layout;",
      "TRUNCATE TABLE warehouse_layout;",
      "TRUNCATE TABLE warehouse_layout CASCADE;"
    ]
  },
  {
    "statements": [
      "TRUNCATE TABLE warehouse_layout;",
      "TRUNCATE TABLE order_details;",
      "TRUNCATE TABLE warehouse_layout;",
      "TRUNCATE TABLE order_details;"
    ]
  },
  {
    "statements": [
      "TRUNCATE TABLE Orders;",
      "TRUNCATE WarehouseLocations;",
      "TRUNCATE TABLE Orders;",
      "TRUNCATE TABLE Inventory;"
    ]
  },
  {
    "statements": [
      "TRUNCATE TABLE WarehouseLayout;",
      "TRUNCATE TABLE Product;",
      "TRUNCATE TABLE OrderItems;",
      "TRUNCATE TABLE Orders;"
    ]
  },
  {
    "statements": [
      "TRUNCATE TABLE order_item;",
      "TRUNCATE TABLE warehouse_inventory;",
      "TRUNCATE TABLE warehouse_inventory;",
      "TRUNCATE TABLE order_item;"
    ]
  }
]